dzip/__init__.py
dzip/__main__.py
dzip/dzip.py
dzip-0.1.dist-info/LICENSE
dzip-0.1.dist-info/METADATA
dzip-0.1.dist-info/WHEEL
dzip-0.1.dist-info/entry_points.txt
dzip-0.1.dist-info/top_level.txt
dzip-0.1.dist-info/RECORD
